{"chunk_definitions":[{"chunk_id":"coyvvjswiby6a","chunk_label":"unnamed-chunk-1","document_id":"CF1ACE72","expansion_state":0,"options":{"engine":"r","label":"unnamed-chunk-12"},"row":8,"row_count":1,"visible":true},{"chunk_id":"chga3mcz6suep","chunk_label":"unnamed-chunk-2","document_id":"CF1ACE72","expansion_state":0,"options":{"engine":"r","label":"unnamed-chunk-6"},"row":12,"row_count":1,"visible":true},{"chunk_id":"cmr0fc8uitby4","chunk_label":"unnamed-chunk-3","document_id":"CF1ACE72","expansion_state":0,"options":{"engine":"r","label":"unnamed-chunk-11"},"row":35,"row_count":1,"visible":true},{"chunk_id":"cdyk5xksf0hur","chunk_label":"Plotting Conditional Summaries","document_id":"CF1ACE72","expansion_state":0,"options":{"engine":"r","label":"Plotting Conditional Summaries"},"row":62,"row_count":1,"visible":true},{"chunk_id":"cilf2qzlol8wk","chunk_label":"unnamed-chunk-4","document_id":"CF1ACE72","expansion_state":0,"options":{"engine":"r","label":"unnamed-chunk-14"},"row":82,"row_count":1,"visible":true},{"chunk_id":"c60d5z3tpsvw8","chunk_label":"unnamed-chunk-5","document_id":"CF1ACE72","expansion_state":0,"options":{"engine":"r","label":"unnamed-chunk-25"},"row":102,"row_count":1,"visible":true},{"chunk_id":"c260vadusb2g8","chunk_label":"unnamed-chunk-6","document_id":"CF1ACE72","expansion_state":0,"options":{"engine":"r","label":"unnamed-chunk-26"},"row":113,"row_count":1,"visible":true},{"chunk_id":"cm7xgwpwfbyh8","chunk_label":"unnamed-chunk-7","document_id":"CF1ACE72","expansion_state":0,"options":{"engine":"r","label":"unnamed-chunk-27"},"row":119,"row_count":1,"visible":true},{"chunk_id":"cnsci9rsfl613","chunk_label":"Cut a Variable","document_id":"CF1ACE72","expansion_state":0,"options":{"engine":"r","label":"Cut a Variable"},"row":152,"row_count":1,"visible":true},{"chunk_id":"c5b5t5fdglg52","chunk_label":"Plotting it All Together","document_id":"CF1ACE72","expansion_state":0,"options":{"engine":"r","label":"Plotting it All Together"},"row":167,"row_count":1,"visible":true},{"chunk_id":"ct8et5mhmmayv","chunk_label":"Friending Rate","document_id":"CF1ACE72","expansion_state":0,"options":{"engine":"r","label":"Friending Rate"},"row":185,"row_count":1,"visible":true},{"chunk_id":"c2eyhe7vgszbz","chunk_label":"Friendships Initiated","document_id":"CF1ACE72","expansion_state":0,"options":{"engine":"r","label":"Friendships Initiated"},"row":203,"row_count":1,"visible":true},{"chunk_id":"cjm493ye4ynsj","chunk_label":"Bias-Variance Tradeoff Revisited","document_id":"CF1ACE72","expansion_state":0,"options":{"engine":"r","label":"Bias-Variance Tradeoff Revisited"},"row":236,"row_count":1,"visible":true},{"chunk_id":"chkgmmvx7r10l","chunk_label":"unnamed-chunk-8","document_id":"CF1ACE72","expansion_state":0,"options":{"engine":"r","label":"unnamed-chunk-35"},"row":254,"row_count":1,"visible":true},{"chunk_id":"c1jn6hca7w1sk","chunk_label":"Histograms Revisited","document_id":"CF1ACE72","expansion_state":0,"options":{"engine":"r","label":"Histograms Revisited"},"row":264,"row_count":1,"visible":true},{"chunk_id":"c2slru4dani0s","chunk_label":"Number of Purchases","document_id":"CF1ACE72","expansion_state":0,"options":{"engine":"r","label":"Number of Purchases"},"row":274,"row_count":1,"visible":true},{"chunk_id":"c9vmef6cz6za5","chunk_label":"Prices over Time","document_id":"CF1ACE72","expansion_state":0,"options":{"engine":"r","label":"Prices over Time"},"row":287,"row_count":1,"visible":true},{"chunk_id":"cit9nlqrsyaf0","chunk_label":"unnamed-chunk-9","document_id":"CF1ACE72","expansion_state":0,"options":{"engine":"r","label":"unnamed-chunk-36"},"row":304,"row_count":1,"visible":true},{"chunk_id":"cbgfiovo116ez","chunk_label":"Looking at Sample of Households","document_id":"CF1ACE72","expansion_state":0,"options":{"engine":"r","label":"Looking at Sample of Households"},"row":314,"row_count":1,"visible":true},{"chunk_id":"c93oudqz22t8o","chunk_label":"unnamed-chunk-10","document_id":"CF1ACE72","expansion_state":0,"options":{"engine":"r","label":"unnamed-chunk-38"},"row":335,"row_count":1,"visible":true}],"chunk_rendered_width":688,"doc_write_time":1524406967}